vaex/viz/__init__.py
vaex/viz/_version.py
vaex/viz/contour.py
vaex/viz/mpl.py
vaex/viz/tensor.py
vaex/viz/vector.py
vaex_viz-0.5.4.dist-info/LICENSE.txt
vaex_viz-0.5.4.dist-info/METADATA
vaex_viz-0.5.4.dist-info/WHEEL
vaex_viz-0.5.4.dist-info/entry_points.txt
vaex_viz-0.5.4.dist-info/top_level.txt
vaex_viz-0.5.4.dist-info/RECORD
