Metadata-Version: 1.0
Name: vaex-viz
Version: 0.5.4
Summary: Visualization for vaex
Home-page: https://www.github.com/maartenbreddels/vaex
Author: Maarten A. Breddels
Author-email: maartenbreddels@gmail.com
License: MIT
Platform: UNKNOWN
